bdscan/__init__.py
bdscan/asyncdata.py
bdscan/bdio.py
bdscan/bdoutput.py
bdscan/bdscanaction.py
bdscan/classAzureProvider.py
bdscan/classCargoComponent.py
bdscan/classComponent.py
bdscan/classComponentList.py
bdscan/classConanComponent.py
bdscan/classCondaComponent.py
bdscan/classDartComponent.py
bdscan/classGitHubProvider.py
bdscan/classGoLangComponent.py
bdscan/classHexComponent.py
bdscan/classMavenComponent.py
bdscan/classNpmComponent.py
bdscan/classNugetComponent.py
bdscan/classPyPiComponent.py
bdscan/classSCMProvider.py
bdscan/globals.py
bdscan/scan.py
bdscan/utils.py
blackduck_direct_scan_action-1.0.1.dist-info/LICENSE
blackduck_direct_scan_action-1.0.1.dist-info/METADATA
blackduck_direct_scan_action-1.0.1.dist-info/WHEEL
blackduck_direct_scan_action-1.0.1.dist-info/entry_points.txt
blackduck_direct_scan_action-1.0.1.dist-info/top_level.txt
blackduck_direct_scan_action-1.0.1.dist-info/RECORD
