Metadata-Version: 2.1
Name: blackduck-direct-scan-action
Version: 1.0.1
Summary: Community Github Action to scan for SCA using Synopsys Black Duck.
Home-page: https://github.com/synopsys-sig-community/blackduck-direct-scan-action
Author: Matthew Brady
Author-email: mbrad@synopsys.com
License: UNKNOWN
Platform: UNKNOWN
Classifier: Programming Language :: Python :: 3
Classifier: License :: OSI Approved :: Apache Software License
Classifier: Operating System :: OS Independent
Requires-Python: >=3.0
License-File: LICENSE
Requires-Dist: blackduck (>=1.0.4)
Requires-Dist: pyGitHub
Requires-Dist: aiohttp
Requires-Dist: blackduck
Requires-Dist: networkx
Requires-Dist: requests
Requires-Dist: semver
Requires-Dist: lxml
Requires-Dist: azure-devops
